omproxy/__init__.py
omproxy/cli.py
omproxy/proxy.py
omproxy-0.3.0.dist-info/METADATA
omproxy-0.3.0.dist-info/WHEEL
omproxy-0.3.0.dist-info/entry_points.txt
omproxy-0.3.0.dist-info/licenses/LICENSE
omproxy-0.3.0.dist-info/RECORD
