Metadata-Version: 2.4
Name: omproxy
Version: 0.3.0
Summary: An open source proxy for MCP servers
License-File: LICENSE
Requires-Python: >=3.12
Requires-Dist: mcp>=1.2.0rc1
Requires-Dist: typer>=0.15.1
